krypy/__init__.py
krypy/_convenience.py
krypy/deflation.py
krypy/linsys.py
krypy/utils.py
krypy/recycling/__init__.py
krypy/recycling/evaluators.py
krypy/recycling/factories.py
krypy/recycling/generators.py
krypy/recycling/linsys.py
krypy-2.2.0.dist-info/LICENSE
krypy-2.2.0.dist-info/METADATA
krypy-2.2.0.dist-info/WHEEL
krypy-2.2.0.dist-info/top_level.txt
krypy-2.2.0.dist-info/RECORD
