Metadata-Version: 2.1
Name: krypy
Version: 2.2.0
Summary: Krylov subspace methods for linear systems
Home-page: https://github.com/andrenarchy/krypy
Author: André Gaul
Author-email: gaul@web-yard.de
License: UNKNOWN
Platform: UNKNOWN
Classifier: Development Status :: 4 - Beta
Classifier: Intended Audience :: Science/Research
Classifier: License :: OSI Approved :: MIT License
Classifier: Operating System :: OS Independent
Classifier: Programming Language :: Python
Classifier: Programming Language :: Python :: 3
Classifier: Topic :: Scientific/Engineering :: Mathematics
Requires-Python: >=3.6
Requires-Dist: numpy (>=1.11)
Requires-Dist: scipy (>=0.17)
